sqltrace/__init__.py
sqltrace/_propagation.py
sqltrace/psycopg.py
sqltrace-0.1.0.dist-info/METADATA
sqltrace-0.1.0.dist-info/WHEEL
sqltrace-0.1.0.dist-info/RECORD
