Metadata-Version: 2.1
Name: sqltrace
Version: 0.1.0
Summary: 
Author: Adrian Garcia Badaracco
Author-email: 1755071+adriangb@users.noreply.github.com
Requires-Python: >=3.8,<4.0
Classifier: Programming Language :: Python :: 3
Classifier: Programming Language :: Python :: 3.8
Classifier: Programming Language :: Python :: 3.9
Classifier: Programming Language :: Python :: 3.10
Classifier: Programming Language :: Python :: 3.11
Classifier: Programming Language :: Python :: 3.12
Requires-Dist: google-cloud-sqlcommenter[opentelemetry] (>=2)
Requires-Dist: httpx (>=0.27.0,<0.28.0)
Requires-Dist: opentelemetry-api (>=1)
Requires-Dist: opentelemetry-sdk (>=1.23.0,<2.0.0)
Requires-Dist: typing-extensions (>=4)
